psoplot/__about__.py
psoplot/__init__.py
psoplot/__utils__.py
psoplot/_subplot.py
psoplot/aanda_plot.py
psoplot/aanda_publication.mplstyle
psoplot/aas_plot.py
psoplot/aas_publication.mplstyle
psoplot/gridplot.py
psoplot/cli/make_movie.py
psoplot-25.5.2.dist-info/METADATA
psoplot-25.5.2.dist-info/WHEEL
psoplot-25.5.2.dist-info/entry_points.txt
psoplot-25.5.2.dist-info/licenses/LICENSE
psoplot-25.5.2.dist-info/RECORD
