Metadata-Version: 2.4
Name: psoplot
Version: 25.5.2
Summary: PSO Plotting Utils
Project-URL: Homepage, https://github.com/astro-pso/psoplot
Project-URL: Bug Tracker, https://github.com/astro-pso/psoplot/issues
Author-email: Alexander Holas <alex.holas@gmx.de>
License-Expression: MIT
License-File: LICENSE
Classifier: Development Status :: 4 - Beta
Classifier: Programming Language :: Python
Classifier: Programming Language :: Python :: 3.8
Classifier: Programming Language :: Python :: 3.9
Classifier: Programming Language :: Python :: 3.10
Classifier: Programming Language :: Python :: 3.11
Classifier: Programming Language :: Python :: 3.12
Classifier: Programming Language :: Python :: Implementation :: CPython
Classifier: Programming Language :: Python :: Implementation :: PyPy
Requires-Python: >=3.8
Requires-Dist: matplotlib>=3.6.0
Requires-Dist: numpy>=1.21.0
Provides-Extra: docs
Requires-Dist: furo; extra == 'docs'
Requires-Dist: sphinx; extra == 'docs'
Requires-Dist: sphinx-copybutton; extra == 'docs'
